graphene_objecttype_from_sqlalchemy_table/__init__.py
graphene_objecttype_from_sqlalchemy_table/convert.py
graphene_objecttype_from_sqlalchemy_table/enum.py
graphene_objecttype_from_sqlalchemy_table/type.py
graphene_objecttype_from_sqlalchemy_table-0.1.2.dist-info/AUTHORS.rst
graphene_objecttype_from_sqlalchemy_table-0.1.2.dist-info/LICENSE
graphene_objecttype_from_sqlalchemy_table-0.1.2.dist-info/METADATA
graphene_objecttype_from_sqlalchemy_table-0.1.2.dist-info/WHEEL
graphene_objecttype_from_sqlalchemy_table-0.1.2.dist-info/top_level.txt
graphene_objecttype_from_sqlalchemy_table-0.1.2.dist-info/RECORD
