Metadata-Version: 2.1
Name: graphene-objecttype-from-sqlalchemy-table
Version: 0.1.2
Summary: Transform SQLAlchemy Table into Graphene ObjectType.
Home-page: https://github.com/Joko013/graphene-objecttype-from-sqlalchemy-table
Author: Jan Klima
Author-email: klima013@gmail.com
License: MIT license
Keywords: graphene_objecttype_from_sqlalchemy_table
Platform: UNKNOWN
Classifier: Development Status :: 2 - Pre-Alpha
Classifier: Intended Audience :: Developers
Classifier: License :: OSI Approved :: MIT License
Classifier: Natural Language :: English
Classifier: Programming Language :: Python :: 3
Classifier: Programming Language :: Python :: 3.6
Classifier: Programming Language :: Python :: 3.7
Classifier: Programming Language :: Python :: 3.8
Requires-Python: >=3.6
Requires-Dist: graphene (<3,>=2.1.3)
Requires-Dist: sqlalchemy (<2,>=1.2)
